{"trial_id": "06", "hyperparameters": {"space": [{"class_name": "Int", "config": {"name": "n_hidden", "default": null, "conditions": [], "min_value": 1, "max_value": 5, "step": 1, "sampling": "linear"}}, {"class_name": "Int", "config": {"name": "n_neurons", "default": null, "conditions": [], "min_value": 1, "max_value": 200, "step": 1, "sampling": "linear"}}, {"class_name": "Float", "config": {"name": "learning_rate", "default": 0.0001, "conditions": [], "min_value": 0.0001, "max_value": 0.01, "step": null, "sampling": "log"}}, {"class_name": "Float", "config": {"name": "l2_reg", "default": 0.0001, "conditions": [], "min_value": 0.0001, "max_value": 100.0, "step": null, "sampling": "log"}}, {"class_name": "Choice", "config": {"name": "optimizer", "default": "sgd", "conditions": [], "values": ["sgd", "nadam"], "ordered": false}}], "values": {"n_hidden": 1, "n_neurons": 56, "learning_rate": 0.005241515692754444, "l2_reg": 0.05070733718569662, "optimizer": "sgd"}}, "metrics": {"metrics": {"loss": {"direction": "min", "observations": [{"value": [261.1848449707031], "step": 18}]}, "val_loss": {"direction": "min", "observations": [{"value": [308.5634765625], "step": 18}]}}}, "score": 308.5634765625, "best_step": 18, "status": "COMPLETED", "message": null}